
{
  "BK-001": {
    "id": "BK-001",
    "bookingId": "BK-001",
    "therapistId": "therapist-01",
    "startedAt": { "_seconds": 1722854400, "_nanoseconds": 0 },
    "endedAt": { "_seconds": 1722858000, "_nanoseconds": 0 },
    "durationMin": 60,
    "events": [
      {
        "type": "start_verification_success",
        "at": { "_seconds": 1722854400, "_nanoseconds": 0 },
        "note": "Patient verified via OTP."
      },
      {
        "type": "session_ended",
        "at": { "_seconds": 1722858000, "_nanoseconds": 0 },
        "note": "Therapist marked session as complete."
      }
    ]
  }
}
